<Properties StartupConfiguration="{9E7D15BB-6162-4FE5-B9B2-16BF472D9A78}|https">
  <MonoDevelop.Ide.ItemProperties.api PreferredExecutionTarget="/System/Volumes/Preboot/Cryptexes/App/System/Applications/Safari.app" />
  <MonoDevelop.Ide.DebuggingService.Breakpoints>
    <BreakpointStore />
  </MonoDevelop.Ide.DebuggingService.Breakpoints>
  <MonoDevelop.Ide.Workspace ActiveConfiguration="Debug" />
  <MonoDevelop.Ide.Workbench ActiveDocument="Entities/User.cs">
    <Files>
      <File FileName="DBContext/DBContext.cs" Line="26" Column="1" />
      <File FileName="Program.cs" Line="24" Column="202" />
      <File FileName="Controllers/AuthentificationController.cs" Line="26" Column="42" />
      <File FileName="AuthService/AuthenticationService.cs" Line="19" Column="1" />
      <File FileName="AuthService/IAthenticationService.cs" Line="8" Column="7" />
      <File FileName="Entities/User.cs" Line="16" Column="1" />
      <File FileName="Models/User.cs" Line="5" Column="27" />
    </Files>
    <Pads>
      <Pad Id="ProjectPad">
        <State name="__root__">
          <Node name="api" expanded="True">
            <Node name="api" expanded="True">
              <Node name="AuthService" expanded="True" />
              <Node name="Controllers" expanded="True" />
              <Node name="DBContext" expanded="True" />
              <Node name="Entities" expanded="True" />
              <Node name="Models" expanded="True" />
              <Node name="Outcomes" expanded="True" />
              <Node name="Properties" expanded="True" />
            </Node>
          </Node>
        </State>
      </Pad>
    </Pads>
  </MonoDevelop.Ide.Workbench>
  <MultiItemStartupConfigurations />
  <MonoDevelop.Ide.DebuggingService.PinnedWatches />
</Properties>